[
  {
    "ContainingType": "BookCrudOperationWIthRestAPI.Controllers.BookController",
    "Method": "CreateBook",
    "RelativePath": "api/Book/Create",
    "HttpMethod": "POST",
    "IsController": true,
    "Order": 0,
    "Parameters": [
      {
        "Name": "bookVm",
        "Type": "BookCrudOperationWIthRestAPI.Models.BookViewModel",
        "IsRequired": true
      }
    ],
    "ReturnTypes": []
  },
  {
    "ContainingType": "BookCrudOperationWIthRestAPI.Controllers.BookController",
    "Method": "DeleteBook",
    "RelativePath": "api/Book/Delete/{id}",
    "HttpMethod": "DELETE",
    "IsController": true,
    "Order": 0,
    "Parameters": [
      {
        "Name": "id",
        "Type": "System.Int32",
        "IsRequired": true
      }
    ],
    "ReturnTypes": []
  },
  {
    "ContainingType": "BookCrudOperationWIthRestAPI.Controllers.BookController",
    "Method": "GetAllBooks",
    "RelativePath": "api/Book/GetAll",
    "HttpMethod": "GET",
    "IsController": true,
    "Order": 0,
    "Parameters": [],
    "ReturnTypes": []
  },
  {
    "ContainingType": "BookCrudOperationWIthRestAPI.Controllers.BookController",
    "Method": "GetBookById",
    "RelativePath": "api/Book/GetById/{id}",
    "HttpMethod": "GET",
    "IsController": true,
    "Order": 0,
    "Parameters": [
      {
        "Name": "id",
        "Type": "System.Int32",
        "IsRequired": true
      }
    ],
    "ReturnTypes": []
  },
  {
    "ContainingType": "BookCrudOperationWIthRestAPI.Controllers.BookController",
    "Method": "GetPosts",
    "RelativePath": "api/Book/GetPosts",
    "HttpMethod": "GET",
    "IsController": true,
    "Order": 0,
    "Parameters": [],
    "ReturnTypes": []
  },
  {
    "ContainingType": "BookCrudOperationWIthRestAPI.Controllers.BookController",
    "Method": "UpdateBook",
    "RelativePath": "api/Book/Update/{id}",
    "HttpMethod": "PUT",
    "IsController": true,
    "Order": 0,
    "Parameters": [
      {
        "Name": "id",
        "Type": "System.Int32",
        "IsRequired": true
      },
      {
        "Name": "bookVm",
        "Type": "BookCrudOperationWIthRestAPI.Models.BookViewModel",
        "IsRequired": true
      }
    ],
    "ReturnTypes": []
  }
]